neon/__init__.py
neon/_validation.py
neon/clamp.py
neon/compare.py
neon/exceptions.py
neon/inspect.py
neon/safe.py
neon/ulp.py
elemental_neon-1.1.1.dist-info/METADATA
elemental_neon-1.1.1.dist-info/WHEEL
elemental_neon-1.1.1.dist-info/licenses/LICENSE
elemental_neon-1.1.1.dist-info/RECORD
