Metadata-Version: 2.4
Name: elemental-neon
Version: 1.1.1
Summary: Near-equality and tolerance arithmetic for floating-point numbers
Project-URL: Homepage, https://github.com/MarsZDF/neon
Project-URL: Documentation, https://github.com/MarsZDF/neon
Project-URL: Repository, https://github.com/MarsZDF/neon
Project-URL: Bug Tracker, https://github.com/MarsZDF/neon/issues
Project-URL: Issues, https://github.com/MarsZDF/neon/issues
Author-email: "Marco Zaccaria Di Fraia, Neon Contributors" <marco.z.difraia@gmail.com>
License-Expression: MIT
License-File: LICENSE
Keywords: approximate,comparison,equality,float,floating-point,math,numerical,precision,tolerance,ulp
Classifier: Development Status :: 5 - Production/Stable
Classifier: Intended Audience :: Developers
Classifier: Intended Audience :: Science/Research
Classifier: License :: OSI Approved :: MIT License
Classifier: Operating System :: OS Independent
Classifier: Programming Language :: Python :: 3
Classifier: Programming Language :: Python :: 3.9
Classifier: Programming Language :: Python :: 3.10
Classifier: Programming Language :: Python :: 3.11
Classifier: Programming Language :: Python :: 3.12
Classifier: Programming Language :: Python :: 3.13
Classifier: Topic :: Scientific/Engineering
Classifier: Topic :: Scientific/Engineering :: Mathematics
Classifier: Topic :: Software Development :: Libraries
Classifier: Topic :: Software Development :: Libraries :: Python Modules
Classifier: Typing :: Typed
Requires-Python: >=3.9
Provides-Extra: test
Requires-Dist: hypothesis>=6.0; extra == 'test'
Requires-Dist: pytest-cov>=4.0; extra == 'test'
Requires-Dist: pytest>=7.0; extra == 'test'
